spike_cluster_score/__init__.py
spike_cluster_score/main.py
spike_cluster_score/scores.py
spike_cluster_score/scs.py
spike_cluster_score-0.0.1.dist-info/LICENSE.txt
spike_cluster_score-0.0.1.dist-info/METADATA
spike_cluster_score-0.0.1.dist-info/WHEEL
spike_cluster_score-0.0.1.dist-info/top_level.txt
spike_cluster_score-0.0.1.dist-info/RECORD
