Metadata-Version: 2.1
Name: spike-cluster-score
Version: 0.0.1
Summary: Spike Cluster Score (SCS) is a clustering performance metric designed with the purpose of spike sorting in mind
Home-page: https://github.com/ArdeleanRichard/Spike-Cluster-Score
Author: Eugen-Richard Ardelean
Author-email: ardeleaneugenrichard@gmail.com
License: MIT
Classifier: License :: OSI Approved :: MIT License
Classifier: Programming Language :: Python :: 3.7
Classifier: Operating System :: OS Independent
Requires-Python: >=3.7
License-File: LICENSE.txt
Requires-Dist: numpy
Requires-Dist: scikit-learn
Provides-Extra: dev
Requires-Dist: twine >=4.0.2 ; extra == 'dev'
